biotmed_settings_sdk/__init__.py
biotmed_settings_sdk/api_client.py
biotmed_settings_sdk/api_response.py
biotmed_settings_sdk/configuration.py
biotmed_settings_sdk/exceptions.py
biotmed_settings_sdk/py.typed
biotmed_settings_sdk/rest.py
biotmed_settings_sdk/api/__init__.py
biotmed_settings_sdk/api/backup_api_api.py
biotmed_settings_sdk/api/code_snippet_api_api.py
biotmed_settings_sdk/api/entity_api_api.py
biotmed_settings_sdk/api/export_import_configuration_api_api.py
biotmed_settings_sdk/api/health_check_api_api.py
biotmed_settings_sdk/api/interception_configuration_api_api.py
biotmed_settings_sdk/api/locale_api_api.py
biotmed_settings_sdk/api/plugin_v2_api_api.py
biotmed_settings_sdk/api/system_api_api.py
biotmed_settings_sdk/api/template_api_api.py
biotmed_settings_sdk/api/translation_api_api.py
biotmed_settings_sdk/models/__init__.py
biotmed_settings_sdk/models/add_locale_request.py
biotmed_settings_sdk/models/attribute_analytics_db_configuration.py
biotmed_settings_sdk/models/attribute_identifier.py
biotmed_settings_sdk/models/backup_request.py
biotmed_settings_sdk/models/backup_response.py
biotmed_settings_sdk/models/base_locale.py
biotmed_settings_sdk/models/base_selectable_value.py
biotmed_settings_sdk/models/basic_attribute_data.py
biotmed_settings_sdk/models/basic_template_data.py
biotmed_settings_sdk/models/built_in_attribute.py
biotmed_settings_sdk/models/category.py
biotmed_settings_sdk/models/code_snippet_response.py
biotmed_settings_sdk/models/create_built_in_attribute.py
biotmed_settings_sdk/models/create_code_snippet_request.py
biotmed_settings_sdk/models/create_custom_attribute.py
biotmed_settings_sdk/models/create_plugin_request.py
biotmed_settings_sdk/models/create_template_attribute.py
biotmed_settings_sdk/models/create_template_request.py
biotmed_settings_sdk/models/credentials.py
biotmed_settings_sdk/models/custom_attribute.py
biotmed_settings_sdk/models/docker_repository_temp_credentials_response.py
biotmed_settings_sdk-2.3.40.dist-info/METADATA
biotmed_settings_sdk-2.3.40.dist-info/WHEEL
biotmed_settings_sdk-2.3.40.dist-info/top_level.txt
biotmed_settings_sdk-2.3.40.dist-info/RECORD
